MANIFEST.in
README.md
requirements.txt
setup.cfg
setup.py
swagger_py_codegen/__init__.py
swagger_py_codegen/__main__.py
swagger_py_codegen/_version.py
swagger_py_codegen/base.py
swagger_py_codegen/command.py
swagger_py_codegen/falcon.py
swagger_py_codegen/flask.py
swagger_py_codegen/jsonschema.py
swagger_py_codegen/parser.py
swagger_py_codegen/sanic.py
swagger_py_codegen/tornado.py
swagger_py_codegen.egg-info/PKG-INFO
swagger_py_codegen.egg-info/SOURCES.txt
swagger_py_codegen.egg-info/dependency_links.txt
swagger_py_codegen.egg-info/entry_points.txt
swagger_py_codegen.egg-info/requires.txt
swagger_py_codegen.egg-info/top_level.txt
swagger_py_codegen/templates/_do_not_change.tpl
swagger_py_codegen/templates/falcon/api.tpl
swagger_py_codegen/templates/falcon/app.tpl
swagger_py_codegen/templates/falcon/blueprint.tpl
swagger_py_codegen/templates/falcon/requirements.tpl
swagger_py_codegen/templates/falcon/routers.tpl
swagger_py_codegen/templates/falcon/specification.tpl
swagger_py_codegen/templates/falcon/validators.tpl
swagger_py_codegen/templates/falcon/view.tpl
swagger_py_codegen/templates/flask/api.tpl
swagger_py_codegen/templates/flask/app.tpl
swagger_py_codegen/templates/flask/blueprint.tpl
swagger_py_codegen/templates/flask/requirements.tpl
swagger_py_codegen/templates/flask/routers.tpl
swagger_py_codegen/templates/flask/specification.tpl
swagger_py_codegen/templates/flask/validators.tpl
swagger_py_codegen/templates/flask/view.tpl
swagger_py_codegen/templates/jsonschema/schemas.tpl
swagger_py_codegen/templates/sanic/api.tpl
swagger_py_codegen/templates/sanic/app.tpl
swagger_py_codegen/templates/sanic/blueprint.tpl
swagger_py_codegen/templates/sanic/requirements.tpl
swagger_py_codegen/templates/sanic/routers.tpl
swagger_py_codegen/templates/sanic/schemas.tpl
swagger_py_codegen/templates/sanic/specification.tpl
swagger_py_codegen/templates/sanic/validators.tpl
swagger_py_codegen/templates/sanic/view.tpl
swagger_py_codegen/templates/tornado/api.tpl
swagger_py_codegen/templates/tornado/app.tpl
swagger_py_codegen/templates/tornado/blueprint.tpl
swagger_py_codegen/templates/tornado/core.tpl
swagger_py_codegen/templates/tornado/requirements.tpl
swagger_py_codegen/templates/tornado/routers.tpl
