Metadata-Version: 1.1
Name: swagger-py-codegen
Version: 0.3.3
Summary: Generate Flask code from Swagger docs.
Home-page: http://github.com/guokr/swagger-py-codegen
Author: Rejown
Author-email: rejown@gmail.com
License: UNKNOWN
Platform: UNKNOWN
Classifier: Development Status :: 3 - Alpha
Classifier: License :: OSI Approved :: MIT License
Classifier: Programming Language :: Python :: 2.7
Classifier: Programming Language :: Python :: 3
